parenting/__init__.py
parenting/aunt.py
parenting/brother.py
parenting/daddy.py
parenting/friend.py
parenting/grandma.py
parenting/grandpa.py
parenting/mommy.py
parenting/partner.py
parenting/sister.py
parenting/uncle.py
parenting-0.0.4.2.dist-info/LICENSE
parenting-0.0.4.2.dist-info/METADATA
parenting-0.0.4.2.dist-info/WHEEL
parenting-0.0.4.2.dist-info/top_level.txt
parenting-0.0.4.2.dist-info/RECORD
