Metadata-Version: 2.1
Name: parenting
Version: 0.0.4.2
Summary: parenting the Python way
Home-page: https://github.com/till-io/parenting.git
Author: Lukas Jan Stroemsdoerfer
Author-email: ljstroemsdoerfer@gmail.com
License: MIT
Platform: UNKNOWN
